mikrotools-0.7.0.dist-info/METADATA
mikrotools-0.7.0.dist-info/WHEEL
mikrotools-0.7.0.dist-info/entry_points.txt
mikrotools-0.7.0.dist-info/licenses/LICENSE
mikrotools/__init__.py
mikrotools/cli/__init__.py
mikrotools/cli/options.py
mikrotools/cli/progress.py
mikrotools/cli/utils.py
mikrotools/config/__init__.py
mikrotools/config/configmanager.py
mikrotools/config/main.py
mikrotools/config/models.py
mikrotools/hoststools/__init__.py
mikrotools/hoststools/common.py
mikrotools/hoststools/models/__init__.py
mikrotools/hoststools/models/base.py
mikrotools/hoststools/models/mikrotik.py
mikrotools/hoststools/models/operations.py
mikrotools/inventory/__init__.py
mikrotools/inventory/factory.py
mikrotools/inventory/models.py
mikrotools/inventory/protocol.py
mikrotools/inventory/providers/__init__.py
mikrotools/inventory/providers/file.py
mikrotools/inventory/providers/netbox.py
mikrotools/inventory/providers/single.py
mikrotools/inventory/providers/static.py
mikrotools/mikromanager.py
mikrotools/netapi/__init__.py
mikrotools/netapi/mikrotik/__init__.py
mikrotools/netapi/mikrotik/client.py
mikrotools/netapi/mikrotik/filters.py
mikrotools/netapi/mikrotik/manager.py
mikrotools/netapi/mikrotik/models/__init__.py
mikrotools/netapi/mikrotik/models/base.py
mikrotools/netapi/mikrotik/models/system.py
mikrotools/plugins/__init__.py
mikrotools/plugins/backup/__init__.py
mikrotools/plugins/backup/cli.py
mikrotools/plugins/backup/utils.py
mikrotools/plugins/execute/__init__.py
mikrotools/plugins/execute/cli.py
mikrotools/plugins/execute/utils.py
mikrotools/plugins/list_routers/__init__.py
mikrotools/plugins/list_routers/cli.py
mikrotools/plugins/list_routers/utils.py
mikrotools/plugins/reboot/__init__.py
mikrotools/plugins/reboot/cli.py
mikrotools/plugins/upgrade/__init__.py
mikrotools/plugins/upgrade/cli.py
mikrotools/plugins/upgrade/progress.py
mikrotools/plugins/upgrade/types.py
mikrotools/plugins/upgrade/utils.py
mikrotools/tools/__init__.py
mikrotools/tools/asynctools.py
mikrotools/tools/cleanup.py
mikrotools/tools/colors.py
mikrotools/tools/config.py
mikrotools/tools/log.py
mikrotools-0.7.0.dist-info/RECORD
