Metadata-Version: 2.1
Name: mikrotools
Version: 0.7.0
Summary: Mikrotik tools
Author-Email: Maksim Kachur <me@maksimkachur.ru>
License: MIT
Project-URL: Homepage, https://github.com/mcdebugger/mikrotools
Project-URL: Issues, https://github.com/mcdebugger/mikrotools/issues
Requires-Python: >=3.13
Requires-Dist: click>=8.1.8
Requires-Dist: packaging>=24.2
Requires-Dist: paramiko>=3.4.0
Requires-Dist: pydantic>=2.10.6
Requires-Dist: PyYAML>=6.0.1
Requires-Dist: rich>=13.9.4
Requires-Dist: click-option-group>=0.5.6
Requires-Dist: asyncssh>=2.20.0
Requires-Dist: pynetbox>=7.5.0
